setup.py
autover/__init__.py
autover.egg-info/PKG-INFO
autover.egg-info/SOURCES.txt
autover.egg-info/dependency_links.txt
autover.egg-info/top_level.txt
scripts/autover