Metadata-Version: 1.1
Name: autover
Version: 0.0.1
Summary: Autover provides consistent and up-to-date `__version__` strings for Python packages.
Home-page: http://github.com/ioam/autover/
Author: IOAM
Author-email: developers@topographica.org
License: BSD
Platform: Windows
Platform: Mac OS X
Platform: Linux
Classifier: License :: OSI Approved :: BSD License
Classifier: Development Status :: 5 - Production/Stable
Classifier: Programming Language :: Python :: 2.6
Classifier: Programming Language :: Python :: 2.7
Classifier: Programming Language :: Python :: 3
Classifier: Operating System :: OS Independent
Classifier: Intended Audience :: Science/Research
Classifier: Intended Audience :: Developers
Classifier: Natural Language :: English
Classifier: Topic :: Scientific/Engineering
Classifier: Topic :: Software Development :: Libraries
Provides: autover
